pinax_stripe_fixed-0.1.data/scripts/pinax-stripe-fixed
stripe/__init__.py
stripe/admin.py
stripe/apps.py
stripe/conf.py
stripe/forms.py
stripe/hooks.py
stripe/managers.py
stripe/middleware.py
stripe/mixins.py
stripe/models.py
stripe/signals.py
stripe/urls.py
stripe/utils.py
stripe/views.py
stripe/webhooks.py
stripe/actions/__init__.py
stripe/actions/accounts.py
stripe/actions/charges.py
stripe/actions/coupons.py
stripe/actions/customers.py
stripe/actions/events.py
stripe/actions/exceptions.py
stripe/actions/externalaccounts.py
stripe/actions/invoices.py
stripe/actions/plans.py
stripe/actions/refunds.py
stripe/actions/sources.py
stripe/actions/subscriptions.py
stripe/actions/transfers.py
stripe/management/__init__.py
stripe/management/commands/__init__.py
stripe/management/commands/init_customers.py
stripe/management/commands/sync_coupons.py
stripe/management/commands/sync_customers.py
stripe/management/commands/sync_plans.py
stripe/management/commands/update_charge_availability.py
stripe/migrations/0001_initial.py
stripe/migrations/0002_auto_20151205_1451.py
stripe/migrations/0003_make_cvc_check_blankable.py
stripe/migrations/0004_plan_metadata.py
stripe/migrations/0005_auto_20161006_1445.py
stripe/migrations/0006_coupon.py
stripe/migrations/0007_auto_20170108_1202.py
stripe/migrations/0008_auto_20170509_1736.py
stripe/migrations/0009_auto_20170825_1841.py
stripe/migrations/0010_connect.py
stripe/migrations/0011_auto_20171121_1648.py
stripe/migrations/0011_auto_20171123_2016.py
stripe/migrations/0013_charge_outcome.py
stripe/migrations/0014_auto_20180413_1959.py
stripe/migrations/0014_blank_with_null.py
stripe/migrations/__init__.py
stripe/templatetags/__init__.py
stripe/templatetags/stripe.py
stripe/tests/__init__.py
stripe/tests/hooks.py
stripe/tests/settings.py
stripe/tests/test_actions.py
stripe/tests/test_admin.py
stripe/tests/test_commands.py
stripe/tests/test_email.py
stripe/tests/test_event.py
stripe/tests/test_forms.py
stripe/tests/test_hooks.py
pinax_stripe_fixed-0.1.dist-info/METADATA
pinax_stripe_fixed-0.1.dist-info/WHEEL
pinax_stripe_fixed-0.1.dist-info/top_level.txt
pinax_stripe_fixed-0.1.dist-info/RECORD
